descript/__init__.py
descript/ion.py
descript/ion.py.orig
descript-0.1.1.dist-info/LICENSE.md
descript-0.1.1.dist-info/WHEEL
descript-0.1.1.dist-info/METADATA
descript-0.1.1.dist-info/RECORD
